[
  {
    "name": "Pengaturan",
    "type": "main_menu",
    "visibility": [
      "application-read",
      "role-read",
      "menu-read",
      "admin-read",
      "whatsapp-api-config-read",
      "template-message-read"
    ],
    "url": "#",
    "icon": "cog-outline",
    "sub_menu": [
      {
        "name": "Aplikasi",
        "type": "sub_menu",
        "visibility": ["application-read"],
        "url": "/application",
        "icon": "apps"
      },
      {
        "name": "Role",
        "type": "sub_menu",
        "visibility": ["role-read"],
        "url": "/role",
        "icon": "shield-check-outline"
      },
      {
        "name": "Menu",
        "type": "sub_menu",
        "visibility": ["menu-read"],
        "url": "/menu",
        "icon": "menu"
      },
      {
        "name": "Admin",
        "type": "sub_menu",
        "visibility": ["admin-read"],
        "url": "/admin",
        "icon": "shield-account-outline"
      },
      {
        "name": "Whatsapp API",
        "type": "sub_menu",
        "visibility": ["whatsapp-api-config-read"],
        "url": "/whatsapp-api-config",
        "icon": "chat-outline"
      },
      {
        "name": "Template Pesan",
        "type": "sub_menu",
        "visibility": ["template-message-read"],
        "url": "/template-message",
        "icon": "message-cog-outline"
      }
    ]
  }
]